{
  "content": {
    "entity": [
      {
        "id": "374",
        "vehicle": {
          "current_status": "IN_TRANSIT_TO",
          "position": {
            "bearing": 206,
            "latitude": 49.8923225402832,
            "longitude": 2.3075132369995117,
            "speed": 8
          },
          "stop_id": "15",
          "timestamp": "1727802226",
          "trip": {
            "route_id": "L",
            "trip_id": "2-L-1-B-182900"
          },
          "vehicle": {
            "id": "374",
            "label": "374"
          }
        }
      },
      {
        "id": "718",
        "vehicle": {
          "current_status": "STOPPED_AT",
          "position": {
            "bearing": 25,
            "latitude": 49.89435958862305,
            "longitude": 2.3092076778411865
          },
          "stop_id": "16",
          "timestamp": "1727802226",
          "trip": {
            "direction_id": 1,
            "route_id": "N2",
            "trip_id": "2-N2-17-B-183202"
          },
          "vehicle": {
            "id": "718",
            "label": "718"
          }
        }
      },
      {
        "id": "178",
        "vehicle": {
          "current_status": "IN_TRANSIT_TO",
          "position": {
            "bearing": 28,
            "latitude": 49.88124084472656,
            "longitude": 2.254844903945923,
            "speed": 8
          },
          "stop_id": "25",
          "timestamp": "1727802196",
          "trip": {
            "route_id": "7",
            "trip_id": "2-7-15-B-185301"
          },
          "vehicle": {
            "id": "178",
            "label": "178"
          }
        }
      },
      {
        "id": "810",
        "vehicle": {
          "current_status": "STOPPED_AT",
          "position": {
            "bearing": 136,
            "latitude": 49.85432434082031,
            "longitude": 2.3985395431518555,
            "speed": 7
          },
          "stop_id": "30",
          "timestamp": "1727802226",
          "trip": {
            "direction_id": 1,
            "route_id": "13",
            "trip_id": "2-13-11-B-185800"
          },
          "vehicle": {
            "id": "810",
            "label": "810"
          }
        }
      },
      {
        "id": "804",
        "vehicle": {
          "current_status": "IN_TRANSIT_TO",
          "position": {
            "bearing": 347,
            "latitude": 49.93612289428711,
            "longitude": 2.3620975017547607,
            "speed": 11
          },
          "stop_id": "33",
          "timestamp": "1727802216",
          "trip": {
            "route_id": "9",
            "trip_id": "2-9-8-B-175700"
          },
          "vehicle": {
            "id": "804",
            "label": "804"
          }
        }
      },
      {
        "id": "344",
        "vehicle": {
          "current_status": "IN_TRANSIT_TO",
          "position": {
            "bearing": 312,
            "latitude": 49.89175796508789,
            "longitude": 2.28816819190979,
            "speed": 8
          },
          "stop_id": "63",
          "timestamp": "1727802226",
          "trip": {
            "direction_id": 1,
            "route_id": "N4",
            "trip_id": "2-N4-8-B-183000"
          },
          "vehicle": {
            "id": "344",
            "label": "344"
          }
        }
      },
      {
        "id": "331",
        "vehicle": {
          "current_status": "IN_TRANSIT_TO",
          "position": {
            "bearing": 282,
            "latitude": 49.87083435058594,
            "longitude": 2.261265993118286,
            "speed": 10
          },
          "stop_id": "102",
          "timestamp": "1727802226",
          "trip": {
            "route_id": "L",
            "trip_id": "2-L-7-B-180900"
          },
          "vehicle": {
            "id": "331",
            "label": "331"
          }
        }
      },
      {
        "id": "741",
        "vehicle": {
          "current_status": "IN_TRANSIT_TO",
          "position": {
            "bearing": 282,
            "latitude": 49.87617111206055,
            "longitude": 2.299867630004883
          },
          "stop_id": "107",
          "timestamp": "1727802226",
          "trip": {
            "direction_id": 1,
            "route_id": "N3",
            "trip_id": "2-N3-16-B-185301"
          },
          "vehicle": {
            "id": "741",
            "label": "741"
          }
        }
      },
      {
        "id": "733",
        "vehicle": {
          "current_status": "IN_TRANSIT_TO",
          "position": {
            "bearing": 103,
            "latitude": 49.925636291503906,
            "longitude": 2.3177013397216797,
            "speed": 6
          },
          "stop_id": "124",
          "timestamp": "1727802226",
          "vehicle": {
            "id": "733",
            "label": "733"
          }
        }
      },
      {
        "id": "815",
        "vehicle": {
          "current_status": "IN_TRANSIT_TO",
          "position": {
            "bearing": 26,
            "latitude": 49.89168167114258,
            "longitude": 2.3072080612182617
          },
          "stop_id": "128",
          "timestamp": "1727802226",
          "trip": {
            "route_id": "7",
            "trip_id": "2-7-11-B-182101"
          },
          "vehicle": {
            "id": "815",
            "label": "815"
          }
        }
      },
      {
        "id": "816",
        "vehicle": {
          "current_status": "STOPPED_AT",
          "position": {
            "bearing": 26,
            "latitude": 49.89138412475586,
            "longitude": 2.306999683380127
          },
          "stop_id": "128",
          "timestamp": "1727802226",
          "trip": {
            "route_id": "9",
            "trip_id": "2-9-7-B-182400"
          },
          "vehicle": {
            "id": "816",
            "label": "816"
          }
        }
      },
      {
        "id": "805",
        "vehicle": {
          "current_status": "IN_TRANSIT_TO",
          "position": {
            "bearing": 26,
            "latitude": 49.891761779785156,
            "longitude": 2.3072774410247803
          },
          "stop_id": "128",
          "timestamp": "1727802216",
          "trip": {
            "direction_id": 1,
            "route_id": "11",
            "trip_id": "2-11-7-B-181900"
          },
          "vehicle": {
            "id": "805",
            "label": "805"
          }
        }
      },
      {
        "id": "173",
        "vehicle": {
          "current_status": "IN_TRANSIT_TO",
          "position": {
            "bearing": 233,
            "latitude": 49.89976501464844,
            "longitude": 2.267852783203125,
            "speed": 1
          },
          "stop_id": "130",
          "timestamp": "1727802226",
          "trip": {
            "direction_id": 1,
            "route_id": "7",
            "trip_id": "2-7-14-B-181300"
          },
          "vehicle": {
            "id": "173",
            "label": "173"
          }
        }
      },
      {
        "id": "341",
        "vehicle": {
          "current_status": "STOPPED_AT",
          "position": {
            "bearing": 69,
            "latitude": 49.87068557739258,
            "longitude": 2.333017587661743
          },
          "stop_id": "137",
          "timestamp": "1727802226",
          "trip": {
            "route_id": "N4",
            "trip_id": "2-N4-10-B-183000"
          },
          "vehicle": {
            "id": "341",
            "label": "341"
          }
        }
      },
      {
        "id": "340",
        "vehicle": {
          "current_status": "STOPPED_AT",
          "position": {
            "bearing": 110,
            "latitude": 49.89809036254883,
            "longitude": 2.267174005508423
          },
          "stop_id": "170",
          "timestamp": "1727802076",
          "trip": {
            "route_id": "N4",
            "trip_id": "2-N4-12-B-191400"
          },
          "vehicle": {
            "id": "340",
            "label": "340"
          }
        }
      },
      {
        "id": "337",
        "vehicle": {
          "current_status": "IN_TRANSIT_TO",
          "position": {
            "bearing": 25,
            "latitude": 49.90122604370117,
            "longitude": 2.3142359256744385
          },
          "stop_id": "170",
          "timestamp": "1727802226",
          "vehicle": {
            "id": "337",
            "label": "337"
          }
        }
      },
      {
        "id": "358",
        "vehicle": {
          "current_status": "STOPPED_AT",
          "position": {
            "bearing": 147,
            "latitude": 49.91401290893555,
            "longitude": 2.2458794116973877
          },
          "stop_id": "292",
          "timestamp": "1727801836",
          "trip": {
            "direction_id": 1,
            "route_id": "8",
            "trip_id": "2-8-9-B-191400"
          },
          "vehicle": {
            "id": "358",
            "label": "358"
          }
        }
      },
      {
        "id": "376",
        "vehicle": {
          "current_status": "STOPPED_AT",
          "position": {
            "bearing": 117,
            "latitude": 49.91379928588867,
            "longitude": 2.3231563568115234,
            "speed": 9
          },
          "stop_id": "306",
          "timestamp": "1727802226",
          "trip": {
            "route_id": "L",
            "trip_id": "2-L-5-B-185000"
          },
          "vehicle": {
            "id": "376",
            "label": "376"
          }
        }
      },
      {
        "id": "165",
        "vehicle": {
          "current_status": "IN_TRANSIT_TO",
          "position": {
            "bearing": 229,
            "latitude": 49.88401794433594,
            "longitude": 2.2826452255249023
          },
          "stop_id": "318",
          "timestamp": "1727802226",
          "trip": {
            "route_id": "5B",
            "trip_id": "2-5B-3-B-175800"
          },
          "vehicle": {
            "id": "165",
            "label": "165"
          }
        }
      },
      {
        "id": "716",
        "vehicle": {
          "current_status": "IN_TRANSIT_TO",
          "position": {
            "bearing": 45,
            "latitude": 49.886470794677734,
            "longitude": 2.291355609893799
          },
          "stop_id": "330",
          "timestamp": "1727802226",
          "vehicle": {
            "id": "716",
            "label": "716"
          }
        }
      },
      {
        "id": "734",
        "vehicle": {
          "current_status": "IN_TRANSIT_TO",
          "position": {
            "bearing": 274,
            "latitude": 49.88861846923828,
            "longitude": 2.3025684356689453,
            "speed": 3
          },
          "stop_id": "335",
          "timestamp": "1727802226",
          "trip": {
            "route_id": "N3",
            "trip_id": "2-N3-1-B-184100"
          },
          "vehicle": {
            "id": "734",
            "label": "734"
          }
        }
      },
      {
        "id": "139",
        "vehicle": {
          "current_status": "IN_TRANSIT_TO",
          "position": {
            "bearing": 349,
            "latitude": 49.88919448852539,
            "longitude": 2.3028736114501953,
            "speed": 3
          },
          "stop_id": "335",
          "timestamp": "1727802226",
          "trip": {
            "direction_id": 1,
            "route_id": "9",
            "trip_id": "2-9-10-B-182800"
          },
          "vehicle": {
            "id": "139",
            "label": "139"
          }
        }
      },
      {
        "id": "181",
        "vehicle": {
          "current_status": "STOPPED_AT",
          "position": {
            "bearing": 195,
            "latitude": 49.891727447509766,
            "longitude": 2.3070690631866455
          },
          "stop_id": "335",
          "timestamp": "1727802226",
          "trip": {
            "route_id": "11",
            "trip_id": "2-11-4-B-183400"
          },
          "vehicle": {
            "id": "181",
            "label": "181"
          }
        }
      },
      {
        "id": "803",
        "vehicle": {
          "current_status": "STOPPED_AT",
          "position": {
            "bearing": 192,
            "latitude": 49.89174270629883,
            "longitude": 2.3070690631866455
          },
          "stop_id": "335",
          "timestamp": "1727802146",
          "trip": {
            "route_id": "15",
            "trip_id": "2-15-10-B-190500"
          },
          "vehicle": {
            "id": "803",
            "label": "803"
          }
        }
      },
      {
        "id": "333",
        "vehicle": {
          "current_status": "STOPPED_AT",
          "position": {
            "bearing": 22,
            "latitude": 49.8916130065918,
            "longitude": 2.3071279525756836
          },
          "stop_id": "336",
          "timestamp": "1727802196",
          "trip": {
            "route_id": "8",
            "trip_id": "2-8-8-B-190501"
          },
          "vehicle": {
            "id": "333",
            "label": "333"
          }
        }
      },
      {
        "id": "813",
        "vehicle": {
          "current_status": "IN_TRANSIT_TO",
          "position": {
            "bearing": 80,
            "latitude": 49.87136459350586,
            "longitude": 2.3195977210998535
          },
          "stop_id": "358",
          "timestamp": "1727802226",
          "trip": {
            "route_id": "5B",
            "trip_id": "2-5B-8-B-184400"
          },
          "vehicle": {
            "id": "813",
            "label": "813"
          }
        }
      },
      {
        "id": "174",
        "vehicle": {
          "current_status": "IN_TRANSIT_TO",
          "position": {
            "bearing": 26,
            "latitude": 49.897682189941406,
            "longitude": 2.3115687370300293,
            "speed": 13
          },
          "stop_id": "358",
          "timestamp": "1727802226",
          "vehicle": {
            "id": "174",
            "label": "174"
          }
        }
      },
      {
        "id": "811",
        "vehicle": {
          "current_status": "IN_TRANSIT_TO",
          "position": {
            "bearing": 25,
            "latitude": 49.88904571533203,
            "longitude": 2.2900328636169434
          },
          "stop_id": "383",
          "timestamp": "1727802226",
          "trip": {
            "route_id": "5A",
            "trip_id": "2-5A-6-B-184500"
          },
          "vehicle": {
            "id": "811",
            "label": "811"
          }
        }
      },
      {
        "id": "189",
        "vehicle": {
          "current_status": "STOPPED_AT",
          "position": {
            "bearing": 193,
            "latitude": 49.887847900390625,
            "longitude": 2.3029580116271973
          },
          "stop_id": "401",
          "timestamp": "1727802226",
          "trip": {
            "route_id": "6",
            "trip_id": "2-6-3-B-184000"
          },
          "vehicle": {
            "id": "189",
            "label": "189"
          }
        }
      },
      {
        "id": "372",
        "vehicle": {
          "current_status": "IN_TRANSIT_TO",
          "position": {
            "bearing": 115,
            "latitude": 49.92246627807617,
            "longitude": 2.303156852722168,
            "speed": 6
          },
          "stop_id": "443",
          "timestamp": "1727802226",
          "trip": {
            "direction_id": 1,
            "route_id": "L",
            "trip_id": "2-L-4-B-174701"
          },
          "vehicle": {
            "id": "372",
            "label": "372"
          }
        }
      },
      {
        "id": "377",
        "vehicle": {
          "current_status": "STOPPED_AT",
          "position": {
            "bearing": 315,
            "latitude": 49.912418365478516,
            "longitude": 2.3242828845977783
          },
          "stop_id": "447",
          "timestamp": "1727802226",
          "trip": {
            "direction_id": 1,
            "route_id": "L",
            "trip_id": "2-L-9-B-181100"
          },
          "vehicle": {
            "id": "377",
            "label": "377"
          }
        }
      },
      {
        "id": "820",
        "vehicle": {
          "current_status": "IN_TRANSIT_TO",
          "position": {
            "bearing": 265,
            "latitude": 49.8868293762207,
            "longitude": 2.343174457550049,
            "speed": 5
          },
          "stop_id": "456",
          "timestamp": "1727802226",
          "trip": {
            "direction_id": 1,
            "route_id": "7",
            "trip_id": "2-7-10-B-185000"
          },
          "vehicle": {
            "id": "820",
            "label": "820"
          }
        }
      },
      {
        "id": "149",
        "vehicle": {
          "current_status": "STOPPED_AT",
          "position": {
            "bearing": 221,
            "latitude": 49.87099838256836,
            "longitude": 2.2432894706726074,
            "speed": 9
          },
          "stop_id": "485",
          "timestamp": "1727802226",
          "trip": {
            "route_id": "11",
            "trip_id": "2-11-13-B-180400"
          },
          "vehicle": {
            "id": "149",
            "label": "149"
          }
        }
      },
      {
        "id": "347",
        "vehicle": {
          "current_status": "IN_TRANSIT_TO",
          "position": {
            "bearing": 85,
            "latitude": 49.87538528442383,
            "longitude": 2.2799315452575684,
            "speed": 5
          },
          "stop_id": "524",
          "timestamp": "1727802226",
          "trip": {
            "direction_id": 1,
            "route_id": "L",
            "trip_id": "2-L-8-B-185401"
          },
          "vehicle": {
            "id": "347",
            "label": "347"
          }
        }
      },
      {
        "id": "180",
        "vehicle": {
          "current_status": "IN_TRANSIT_TO",
          "position": {
            "bearing": 6,
            "latitude": 49.96342849731445,
            "longitude": 2.312746286392212,
            "speed": 18
          },
          "stop_id": "596",
          "timestamp": "1727802226",
          "trip": {
            "direction_id": 1,
            "route_id": "12",
            "trip_id": "2-12-10-B-174800"
          },
          "vehicle": {
            "id": "180",
            "label": "180"
          }
        }
      },
      {
        "id": "809",
        "vehicle": {
          "current_status": "IN_TRANSIT_TO",
          "position": {
            "bearing": 235,
            "latitude": 49.87520980834961,
            "longitude": 2.329307794570923,
            "speed": 5
          },
          "stop_id": "611",
          "timestamp": "1727802226",
          "trip": {
            "route_id": "5A",
            "trip_id": "2-5A-1-B-181700"
          },
          "vehicle": {
            "id": "809",
            "label": "809"
          }
        }
      },
      {
        "id": "818",
        "vehicle": {
          "current_status": "IN_TRANSIT_TO",
          "position": {
            "bearing": 38,
            "latitude": 49.87655258178711,
            "longitude": 2.2513651847839355,
            "speed": 5
          },
          "stop_id": "637",
          "timestamp": "1727802226",
          "trip": {
            "direction_id": 1,
            "route_id": "7",
            "trip_id": "2-7-12-B-175600"
          },
          "vehicle": {
            "id": "818",
            "label": "818"
          }
        }
      },
      {
        "id": "135",
        "vehicle": {
          "current_status": "IN_TRANSIT_TO",
          "position": {
            "bearing": 122,
            "latitude": 49.85433578491211,
            "longitude": 2.323922634124756,
            "speed": 23
          },
          "stop_id": "652",
          "timestamp": "1727802226",
          "vehicle": {
            "id": "135",
            "label": "135"
          }
        }
      },
      {
        "id": "186",
        "vehicle": {
          "current_status": "STOPPED_AT",
          "position": {
            "bearing": 264,
            "latitude": 49.87236404418945,
            "longitude": 2.3224871158599854,
            "speed": 5
          },
          "stop_id": "709",
          "timestamp": "1727802226",
          "trip": {
            "route_id": "5A",
            "trip_id": "2-5A-7-B-175400"
          },
          "vehicle": {
            "id": "186",
            "label": "186"
          }
        }
      },
      {
        "id": "156",
        "vehicle": {
          "current_status": "IN_TRANSIT_TO",
          "position": {
            "bearing": 84,
            "latitude": 49.876792907714844,
            "longitude": 2.2589786052703857,
            "speed": 8
          },
          "stop_id": "906",
          "timestamp": "1727802226",
          "vehicle": {
            "id": "156",
            "label": "156"
          }
        }
      },
      {
        "id": "735",
        "vehicle": {
          "current_status": "STOPPED_AT",
          "position": {
            "bearing": 306,
            "latitude": 49.860198974609375,
            "longitude": 2.2763097286224365
          },
          "stop_id": "957",
          "timestamp": "1727801876",
          "vehicle": {
            "id": "735",
            "label": "735"
          }
        }
      },
      {
        "id": "822",
        "vehicle": {
          "current_status": "STOPPED_AT",
          "position": {
            "bearing": 270,
            "latitude": 49.89814758300781,
            "longitude": 2.3559908866882324
          },
          "stop_id": "981",
          "timestamp": "1727802046",
          "trip": {
            "direction_id": 1,
            "route_id": "7",
            "trip_id": "2-7-4-B-191500"
          },
          "vehicle": {
            "id": "822",
            "label": "822"
          }
        }
      },
      {
        "id": "151",
        "vehicle": {
          "current_status": "STOPPED_AT",
          "position": {
            "bearing": 287,
            "latitude": 49.895450592041016,
            "longitude": 2.2966010570526123,
            "speed": 6
          },
          "stop_id": "988",
          "timestamp": "1727802226",
          "trip": {
            "direction_id": 1,
            "route_id": "7",
            "trip_id": "2-7-17-B-183100"
          },
          "vehicle": {
            "id": "151",
            "label": "151"
          }
        }
      },
      {
        "id": "343",
        "vehicle": {
          "current_status": "STOPPED_AT",
          "position": {
            "bearing": 121,
            "latitude": 49.888641357421875,
            "longitude": 2.311753988265991
          },
          "stop_id": "992",
          "timestamp": "1727802226",
          "trip": {
            "route_id": "N4",
            "trip_id": "2-N4-4-B-184300"
          },
          "vehicle": {
            "id": "343",
            "label": "343"
          }
        }
      },
      {
        "id": "338",
        "vehicle": {
          "current_status": "STOPPED_AT",
          "position": {
            "bearing": 304,
            "latitude": 49.88882827758789,
            "longitude": 2.3113787174224854,
            "speed": 2
          },
          "stop_id": "993",
          "timestamp": "1727802226",
          "trip": {
            "direction_id": 1,
            "route_id": "N4",
            "trip_id": "2-N4-5-B-184200"
          },
          "vehicle": {
            "id": "338",
            "label": "338"
          }
        }
      },
      {
        "id": "821",
        "vehicle": {
          "current_status": "IN_TRANSIT_TO",
          "position": {
            "bearing": 189,
            "latitude": 49.86536407470703,
            "longitude": 2.378953695297241,
            "speed": 7
          },
          "stop_id": "995",
          "timestamp": "1727802226",
          "trip": {
            "direction_id": 1,
            "route_id": "10",
            "trip_id": "2-10-19-B-181401"
          },
          "vehicle": {
            "id": "821",
            "label": "821"
          }
        }
      },
      {
        "id": "819",
        "vehicle": {
          "current_status": "STOPPED_AT",
          "position": {
            "bearing": 89,
            "latitude": 49.91162872314453,
            "longitude": 2.299785852432251,
            "speed": 6
          },
          "stop_id": "1003",
          "timestamp": "1727802226",
          "trip": {
            "direction_id": 1,
            "route_id": "6",
            "trip_id": "2-6-2-B-183000"
          },
          "vehicle": {
            "id": "819",
            "label": "819"
          }
        }
      },
      {
        "id": "711",
        "vehicle": {
          "current_status": "IN_TRANSIT_TO",
          "position": {
            "bearing": 131,
            "latitude": 49.899288177490234,
            "longitude": 2.284282922744751,
            "speed": 7
          },
          "stop_id": "1006",
          "timestamp": "1727802226",
          "trip": {
            "route_id": "N1",
            "trip_id": "2-N1-17-B-184800"
          },
          "vehicle": {
            "id": "711",
            "label": "711"
          }
        }
      },
      {
        "id": "701",
        "vehicle": {
          "current_status": "IN_TRANSIT_TO",
          "position": {
            "bearing": 301,
            "latitude": 49.86838912963867,
            "longitude": 2.3629117012023926,
            "speed": 7
          },
          "stop_id": "1025",
          "timestamp": "1727802226",
          "trip": {
            "direction_id": 1,
            "route_id": "N1",
            "trip_id": "2-N1-5-B-185600"
          },
          "vehicle": {
            "id": "701",
            "label": "701"
          }
        }
      },
      {
        "id": "706",
        "vehicle": {
          "current_status": "STOPPED_AT",
          "position": {
            "bearing": 108,
            "latitude": 49.91383361816406,
            "longitude": 2.2459354400634766
          },
          "stop_id": "1035",
          "timestamp": "1727802036",
          "trip": {
            "route_id": "N1",
            "trip_id": "2-N1-11-B-190900"
          },
          "vehicle": {
            "id": "706",
            "label": "706"
          }
        }
      },
      {
        "id": "703",
        "vehicle": {
          "current_status": "IN_TRANSIT_TO",
          "position": {
            "bearing": 88,
            "latitude": 49.91568374633789,
            "longitude": 2.3173019886016846,
            "speed": 14
          },
          "stop_id": "1035",
          "timestamp": "1727802226",
          "vehicle": {
            "id": "703",
            "label": "703"
          }
        }
      },
      {
        "id": "709",
        "vehicle": {
          "current_status": "STOPPED_AT",
          "position": {
            "bearing": 281,
            "latitude": 49.90452575683594,
            "longitude": 2.274296522140503
          },
          "stop_id": "1038",
          "timestamp": "1727802226",
          "trip": {
            "direction_id": 1,
            "route_id": "N1",
            "trip_id": "2-N1-14-B-182200"
          },
          "vehicle": {
            "id": "709",
            "label": "709"
          }
        }
      },
      {
        "id": "743",
        "vehicle": {
          "current_status": "IN_TRANSIT_TO",
          "position": {
            "bearing": 2,
            "latitude": 49.91330337524414,
            "longitude": 2.254931926727295,
            "speed": 8
          },
          "stop_id": "1040",
          "timestamp": "1727802226",
          "trip": {
            "direction_id": 1,
            "route_id": "N1",
            "trip_id": "2-N1-18-B-180900"
          },
          "vehicle": {
            "id": "743",
            "label": "743"
          }
        }
      },
      {
        "id": "739",
        "vehicle": {
          "current_status": "STOPPED_AT",
          "position": {
            "bearing": 119,
            "latitude": 49.86900329589844,
            "longitude": 2.3611338138580322,
            "speed": 5
          },
          "stop_id": "1041",
          "timestamp": "1727802226",
          "trip": {
            "route_id": "N1",
            "trip_id": "2-N1-12-B-181000"
          },
          "vehicle": {
            "id": "739",
            "label": "739"
          }
        }
      },
      {
        "id": "713",
        "vehicle": {
          "current_status": "IN_TRANSIT_TO",
          "position": {
            "bearing": 349,
            "latitude": 49.88959884643555,
            "longitude": 2.3028037548065186,
            "speed": 4
          },
          "stop_id": "1045",
          "timestamp": "1727802226",
          "trip": {
            "direction_id": 1,
            "route_id": "N1",
            "trip_id": "2-N1-16-B-183400"
          },
          "vehicle": {
            "id": "713",
            "label": "713"
          }
        }
      },
      {
        "id": "728",
        "vehicle": {
          "current_status": "IN_TRANSIT_TO",
          "position": {
            "bearing": 297,
            "latitude": 49.8681640625,
            "longitude": 2.280411958694458,
            "speed": 4
          },
          "stop_id": "1050",
          "timestamp": "1727802226",
          "trip": {
            "route_id": "N3",
            "trip_id": "2-N3-6-B-182400"
          },
          "vehicle": {
            "id": "728",
            "label": "728"
          }
        }
      },
      {
        "id": "715",
        "vehicle": {
          "current_status": "IN_TRANSIT_TO",
          "position": {
            "bearing": 86,
            "latitude": 49.876792907714844,
            "longitude": 2.259409189224243,
            "speed": 5
          },
          "stop_id": "1052",
          "timestamp": "1727802226",
          "trip": {
            "direction_id": 1,
            "route_id": "N2",
            "trip_id": "2-N2-5-B-185402"
          },
          "vehicle": {
            "id": "715",
            "label": "715"
          }
        }
      },
      {
        "id": "190",
        "vehicle": {
          "current_status": "IN_TRANSIT_TO",
          "position": {
            "bearing": 191,
            "latitude": 49.912017822265625,
            "longitude": 2.2452878952026367
          },
          "stop_id": "1061",
          "timestamp": "1727802226",
          "trip": {
            "route_id": "16",
            "trip_id": "2-16-5-B-183001"
          },
          "vehicle": {
            "id": "190",
            "label": "190"
          }
        }
      },
      {
        "id": "719",
        "vehicle": {
          "current_status": "STOPPED_AT",
          "position": {
            "bearing": 89,
            "latitude": 49.911617279052734,
            "longitude": 2.2978672981262207
          },
          "stop_id": "1075",
          "timestamp": "1727802186",
          "trip": {
            "route_id": "N2",
            "trip_id": "2-N2-9-B-190400"
          },
          "vehicle": {
            "id": "719",
            "label": "719"
          }
        }
      },
      {
        "id": "702",
        "vehicle": {
          "current_status": "IN_TRANSIT_TO",
          "position": {
            "bearing": 90,
            "latitude": 49.91063690185547,
            "longitude": 2.3154690265655518,
            "speed": 6
          },
          "stop_id": "1076",
          "timestamp": "1727802226",
          "vehicle": {
            "id": "702",
            "label": "702"
          }
        }
      },
      {
        "id": "335",
        "vehicle": {
          "current_status": "STOPPED_AT",
          "position": {
            "bearing": 291,
            "latitude": 49.89576721191406,
            "longitude": 2.3045647144317627
          },
          "stop_id": "1078",
          "timestamp": "1727802226",
          "trip": {
            "direction_id": 1,
            "route_id": "L",
            "trip_id": "2-L-6-B-183101"
          },
          "vehicle": {
            "id": "335",
            "label": "335"
          }
        }
      },
      {
        "id": "806",
        "vehicle": {
          "current_status": "IN_TRANSIT_TO",
          "position": {
            "bearing": 288,
            "latitude": 49.89657211303711,
            "longitude": 2.301339626312256,
            "speed": 1
          },
          "stop_id": "1078",
          "timestamp": "1727802226",
          "trip": {
            "route_id": "5B",
            "trip_id": "2-5B-2-B-181900"
          },
          "vehicle": {
            "id": "806",
            "label": "806"
          }
        }
      },
      {
        "id": "710",
        "vehicle": {
          "current_status": "IN_TRANSIT_TO",
          "position": {
            "bearing": 128,
            "latitude": 49.8754768371582,
            "longitude": 2.3478689193725586,
            "speed": 13
          },
          "stop_id": "1079",
          "timestamp": "1727802226",
          "trip": {
            "route_id": "N1",
            "trip_id": "2-N1-15-B-182300"
          },
          "vehicle": {
            "id": "710",
            "label": "710"
          }
        }
      },
      {
        "id": "725",
        "vehicle": {
          "current_status": "STOPPED_AT",
          "position": {
            "bearing": 35,
            "latitude": 49.898475646972656,
            "longitude": 2.296084403991699
          },
          "stop_id": "1097",
          "timestamp": "1727802226",
          "trip": {
            "direction_id": 1,
            "route_id": "N3",
            "trip_id": "2-N3-3-B-183201"
          },
          "vehicle": {
            "id": "725",
            "label": "725"
          }
        }
      },
      {
        "id": "817",
        "vehicle": {
          "current_status": "IN_TRANSIT_TO",
          "position": {
            "bearing": 298,
            "latitude": 49.89289474487305,
            "longitude": 2.3023569583892822,
            "speed": 4
          },
          "stop_id": "1102",
          "timestamp": "1727802226",
          "trip": {
            "direction_id": 1,
            "route_id": "6",
            "trip_id": "2-6-4-B-185000"
          },
          "vehicle": {
            "id": "817",
            "label": "817"
          }
        }
      },
      {
        "id": "729",
        "vehicle": {
          "current_status": "STOPPED_AT",
          "position": {
            "bearing": 205,
            "latitude": 49.91550064086914,
            "longitude": 2.302661180496216,
            "speed": 7
          },
          "stop_id": "1103",
          "timestamp": "1727802226",
          "trip": {
            "route_id": "N3",
            "trip_id": "2-N3-17-B-190100"
          },
          "vehicle": {
            "id": "729",
            "label": "729"
          }
        }
      },
      {
        "id": "720",
        "vehicle": {
          "current_status": "STOPPED_AT",
          "position": {
            "bearing": 72,
            "latitude": 49.871063232421875,
            "longitude": 2.259932041168213
          },
          "stop_id": "1108",
          "timestamp": "1727802226",
          "trip": {
            "route_id": "N2",
            "trip_id": "2-N2-13-B-183000"
          },
          "vehicle": {
            "id": "720",
            "label": "720"
          }
        }
      },
      {
        "id": "723",
        "vehicle": {
          "current_status": "STOPPED_AT",
          "position": {
            "bearing": 270,
            "latitude": 49.88887405395508,
            "longitude": 2.296231269836426,
            "speed": 1
          },
          "stop_id": "1121",
          "timestamp": "1727802226",
          "trip": {
            "route_id": "N2",
            "trip_id": "2-N2-15-B-184400"
          },
          "vehicle": {
            "id": "723",
            "label": "723"
          }
        }
      },
      {
        "id": "169",
        "vehicle": {
          "current_status": "IN_TRANSIT_TO",
          "position": {
            "bearing": 213,
            "latitude": 49.86457061767578,
            "longitude": 2.245704412460327,
            "speed": 12
          },
          "stop_id": "2090",
          "timestamp": "1727802186",
          "trip": {
            "direction_id": 1,
            "route_id": "9",
            "trip_id": "2-9-18-B-175600"
          },
          "vehicle": {
            "id": "169",
            "label": "169"
          }
        }
      },
      {
        "id": "705",
        "vehicle": {
          "current_status": "STOPPED_AT",
          "position": {
            "bearing": 298,
            "latitude": 49.88441467285156,
            "longitude": 2.3224880695343018
          },
          "stop_id": "10000",
          "timestamp": "1727802226",
          "vehicle": {
            "id": "705",
            "label": "705"
          }
        }
      },
      {
        "id": "336",
        "vehicle": {
          "current_status": "STOPPED_AT",
          "position": {
            "bearing": 320,
            "latitude": 49.898494720458984,
            "longitude": 2.372488021850586
          },
          "stop_id": "10000",
          "timestamp": "1727802226",
          "vehicle": {
            "id": "336",
            "label": "336"
          }
        }
      },
      {
        "id": "373",
        "vehicle": {
          "current_status": "STOPPED_AT",
          "position": {
            "bearing": 343,
            "latitude": 49.8742561340332,
            "longitude": 2.369688034057617
          },
          "stop_id": "10000",
          "timestamp": "1727802226",
          "vehicle": {
            "id": "373",
            "label": "373"
          }
        }
      }
    ],
    "header": {
      "gtfs_realtime_version": "2.0",
      "timestamp": "1727802231"
    }
  }
}